extend_inplace/__init__.py
extend_inplace/main.py
extend_inplace/py.typed
extend_inplace-0.0.1.dist-info/LICENSE
extend_inplace-0.0.1.dist-info/METADATA
extend_inplace-0.0.1.dist-info/WHEEL
extend_inplace-0.0.1.dist-info/top_level.txt
extend_inplace-0.0.1.dist-info/RECORD
